YAFPA/__init__.py
YAFPA/__main__.py
YAFPA/common/__init__.py
YAFPA/common/admonition.py
YAFPA/common/conversion.py
YAFPA/common/convert_all.py
YAFPA/common/convert_one.py
YAFPA/common/file_checking.py
YAFPA/common/global_value.py
YAFPA/common/link_conversion.py
YAFPA/common/metadata.py
YAFPA/common/setup_config.py
yafpa-3.0.3.dist-info/LICENSE
yafpa-3.0.3.dist-info/METADATA
yafpa-3.0.3.dist-info/WHEEL
yafpa-3.0.3.dist-info/entry_points.txt
yafpa-3.0.3.dist-info/top_level.txt
yafpa-3.0.3.dist-info/RECORD
