Metadata-Version: 2.1
Name: yafpa
Version: 3.0.3
Summary: A script to share your obsidian vault (in partial way)
Home-page: https://github.com/Mara-Li/YAFPA-python
Author: Mara-Li
Author-email: mara-li@icloud.com
License: AGPL
Keywords: obsidian,obsidian.md,free publish,publish,jekyll,blog
Platform: UNKNOWN
Classifier: Development Status :: 5 - Production/Stable
Classifier: Natural Language :: English
Classifier: Natural Language :: French
Classifier: Topic :: Text Processing :: Markup :: Markdown
Classifier: License :: OSI Approved :: GNU Affero General Public License v3 or later (AGPLv3+)
Classifier: Programming Language :: Python :: 3
Classifier: Programming Language :: Python :: 3.6
Classifier: Programming Language :: Python :: 3.7
Classifier: Programming Language :: Python :: 3.8
Classifier: Programming Language :: Python :: 3.9
Requires-Python: >=3.7
License-File: LICENSE
Requires-Dist: python-dotenv
Requires-Dist: gitpython
Requires-Dist: python-frontmatter
Requires-Dist: pyYAML
Requires-Dist: pyperclip
Requires-Dist: unidecode
